ProteomeClustering/__init__.py
ProteomeClustering/example.py
ProteomeClustering/test2.py
ProteomeClustering/tutorial example.py
ProteomeClustering/CaseStudy/Clustering Analysis.py
ProteomeClustering/CaseStudy/GoTerm.py
ProteomeClustering/CaseStudy/Network.py
ProteomeClustering/CaseStudy/__init__.py
ProteomeClustering/Characterization/Characterization.py
ProteomeClustering/Characterization/Paragraph.py
ProteomeClustering/Characterization/__init__.py
ProteomeClustering/ClusteringMethod/Clustering.py
ProteomeClustering/ClusteringMethod/CommonFunction.py
ProteomeClustering/ClusteringMethod/Consensus.py
ProteomeClustering/ClusteringMethod/GuassianModel.py
ProteomeClustering/ClusteringMethod/Hierarchical.py
ProteomeClustering/ClusteringMethod/KMeans.py
ProteomeClustering/ClusteringMethod/SelfOrganizingMap.py
ProteomeClustering/ClusteringMethod/__init__.py
ProteomeClustering/DataAdapter/CommonFunction.py
ProteomeClustering/DataAdapter/DataChecking.py
ProteomeClustering/DataAdapter/DataCleaning.py
ProteomeClustering/DataAdapter/Filter.py
ProteomeClustering/DataAdapter/Imputation.py
ProteomeClustering/DataAdapter/Log.py
ProteomeClustering/DataAdapter/Nmlz.py
ProteomeClustering/DataAdapter/ReadFiles.py
ProteomeClustering/DataAdapter/Serialization.py
ProteomeClustering/DataAdapter/SortingProtRatioDf.py
ProteomeClustering/DataAdapter/__init__.py
ProteomeClustering/DataStructure/__init__.py
ProteomeClustering/DataStructure/ds_InputRawData.py
ProteomeClustering/DataStructure/ds_ProtClust.py
ProteomeClustering/Scoring/AMIscore.py
ProteomeClustering/Scoring/ARIscore.py
ProteomeClustering/Scoring/BICscore.py
ProteomeClustering/Scoring/CommonFunction.py
ProteomeClustering/Scoring/FeatureEntropy.py
ProteomeClustering/Scoring/FeatureRatio.py
ProteomeClustering/Scoring/Fscore.py
ProteomeClustering/Scoring/GiniScore.py
ProteomeClustering/Scoring/PairedFscore.py
ProteomeClustering/Scoring/PartitionIndex.py
ProteomeClustering/Scoring/PurityScore.py
ProteomeClustering/Scoring/Scores.py
proteomeClusteringtest2-0.0.8.dist-info/LICENSE
proteomeClusteringtest2-0.0.8.dist-info/METADATA
proteomeClusteringtest2-0.0.8.dist-info/WHEEL
proteomeClusteringtest2-0.0.8.dist-info/top_level.txt
proteomeClusteringtest2-0.0.8.dist-info/RECORD
